Chrfinder/Chrfinder.py
Chrfinder/__init__.py
Chrfinder/classify.py
Chrfinder/pka_lookup.py
Chrfinder/pubchemprops.py
Chrfinder/search_pka.py
chrfinder-1.0.1.dist-info/METADATA
chrfinder-1.0.1.dist-info/WHEEL
chrfinder-1.0.1.dist-info/licenses/LICENSE
chrfinder-1.0.1.dist-info/RECORD
