Metadata-Version: 2.3
Name: Chrfinder
Version: 1.0.1
Summary: The package find the best chromatography based on properties of the mixture
Project-URL: source, https://github.com/Averhv/Chrfinder
Project-URL: tracker, https://github.com/Averhv/Chrfinder/issues
Author-email: Anthony Verhoeven <anthony.verhoeven@epfl.ch>
License: MIT License
License-File: LICENSE
Classifier: Development Status :: 3 - Alpha
Classifier: Intended Audience :: Developers
Classifier: License :: OSI Approved :: MIT License
Classifier: Operating System :: OS Independent
Classifier: Programming Language :: Python
Classifier: Programming Language :: Python :: 3
Classifier: Programming Language :: Python :: 3.8
Classifier: Programming Language :: Python :: 3.9
Classifier: Programming Language :: Python :: 3.10
Classifier: Programming Language :: Python :: 3.11
Requires-Python: >=3.10
Requires-Dist: pandas
Requires-Dist: pubchempy
Requires-Dist: requests
Requires-Dist: tk
Provides-Extra: doc
Requires-Dist: furo; extra == 'doc'
Requires-Dist: myst-parser; extra == 'doc'
Requires-Dist: sphinx-copybutton; extra == 'doc'
Requires-Dist: sphinx>=5; extra == 'doc'
Provides-Extra: test
Requires-Dist: genbadge[coverage]; extra == 'test'
Requires-Dist: hypothesis; extra == 'test'
Requires-Dist: pytest; extra == 'test'
Requires-Dist: pytest-cov; extra == 'test'
Requires-Dist: tox; extra == 'test'
